XwsLibrary/FontChoose.py
XwsLibrary/InputBox.py
XwsLibrary/__init__.py
XwsLibrary/setup.py
xwslibrary-1.1.dist-info/METADATA
xwslibrary-1.1.dist-info/WHEEL
xwslibrary-1.1.dist-info/license.txt
xwslibrary-1.1.dist-info/top_level.txt
xwslibrary-1.1.dist-info/RECORD
