Metadata-Version: 2.2
Name: XwsLibrary
Version: 1.1
Summary: wow~高级
Author: XiaoWang
Author-email: wzxddzyj1@outlook.com
License-File: license.txt
Dynamic: author
Dynamic: author-email
Dynamic: summary
